convkan
tests
