Metadata-Version: 2.1
Name: convkan
Version: 0.0.1.2
Summary: Convolutional KAN layer
Author: Vladimir Starostin
Author-email: vladimir.starostin@uni-tuebingen.de
License: MIT
Requires-Python: >=3.8
License-File: LICENSE
Requires-Dist: torch>=2.3.0
Requires-Dist: torchvision>=0.18.0
Requires-Dist: tqdm>=4.66.2
Requires-Dist: pytest>=6.2.4
